[
    {
        "key": "alt+j",
        "command": "cursorLeft",
        "when": "textInputFocus"
    },
    {
        "key": "ctrl+alt+j",
        "command": "cursorWordLeft",
        "when": "textInputFocus && !accessibilityModeEnabled"
    },
    {
        "key": "shift+alt+j",
        "command": "cursorLeftSelect",
        "when": "textInputFocus"
    },
    {
        "key": "ctrl+shift+alt+j",
        "command": "cursorWordLeftSelect",
        "when": "textInputFocus && !accessibilityModeEnabled"
    },
    {
        "key": "alt+l",
        "command": "cursorRight",
        "when": "textInputFocus"
    },
    {
        "key": "ctrl+alt+l",
        "command": "cursorWordRight",
        "when": "textInputFocus && !accessibilityModeEnabled"
    },
    {
        "key": "shift+alt+l",
        "command": "cursorRightSelect",
        "when": "textInputFocus"
    },
    {
        "key": "ctrl+shift+alt+l",
        "command": "cursorWordRightSelect",
        "when": "textInputFocus && !accessibilityModeEnabled"
    },
    {
        "key": "alt+i",
        "command": "cursorUp",
        "when": "textInputFocus"
    },
    {
        "key": "shift+alt+i",
        "command": "cursorUpSelect",
        "when": "textInputFocus"
    },
    {
        "key": "alt+k",
        "command": "cursorDown",
        "when": "textInputFocus"
    },
    {
        "key": "shift+alt+k",
        "command": "cursorDownSelect",
        "when": "textInputFocus"
    },
    {
        "key": "alt+u",
        "command": "cursorHome",
        "when": "textInputFocus"
    },
    {
        "key": "shift+alt+u",
        "command": "cursorHomeSelect",
        "when": "textInputFocus"
    },
    {
        "key": "alt+o",
        "command": "cursorEnd",
        "when": "textInputFocus"
    },
    {
        "key": "shift+alt+o",
        "command": "cursorEndSelect",
        "when": "textInputFocus"
    },
    {
        "key": "alt+n",
        "command": "deleteLeft",
        "when": "textInputFocus"
    },
    {
        "key": "shift+alt+n",
        "command": "deleteRight",
        "when": "textInputFocus"
    },
    {
        "key": "ctrl+d",
        "command": "editor.action.copyLinesDownAction",
        "when": "editorTextFocus && !editorReadonly"
    },
    {
        "key": "alt+d",
        "command": "editor.action.deleteLines",
        "when": "textInputFocus && !editorReadonly"
    },
    {
        "key": "alt+m",
        "command": "extension.multiCommand.execute",
        "args": {
            "sequence": [
                "lineBreakInsert",
                "cursorDown",
                "cursorEnd",
                "cursorHome"
            ]
        },
        "when": "editorTextFocus && !editorReadonly"
    },
    {
        "key": "ctrl+num /",
        "command": "editor.action.commentLine",
        "when": "editorTextFocus && !editorReadonly"
    },
    {
        "key": "alt+7",
        "command": "editor.action.commentLine",
        "when": "editorTextFocus && !editorReadonly"
    },
    {
        "key": "alt+w",
        "command": "editor.action.addSelectionToNextFindMatch",
        "when": "editorFocus"
    },
    {
        "key": "sift+alt+w",
        "command": "editor.action.addSelectionToPreviousFindMatch",
        "when": "editorFocus"
    },
    {
        "key": "ctrl+alt+i",
        "command": "editor.action.insertCursorAbove",
        "when": "editorFocus"
    },
    {
        "key": "ctrl+alt+k",
        "command": "editor.action.insertCursorBelow",
        "when": "editorFocus"
    },
    {
        "key": "alt+e",
        "command": "editor.action.revealFileInOS",
        "when": "editorFocus"
    }
]